MANIFEST.in
README.txt
setup.cfg
setup.py
docs/HISTORY.txt
raptus/__init__.py
raptus.securelogin.egg-info/PKG-INFO
raptus.securelogin.egg-info/SOURCES.txt
raptus.securelogin.egg-info/dependency_links.txt
raptus.securelogin.egg-info/entry_points.txt
raptus.securelogin.egg-info/namespace_packages.txt
raptus.securelogin.egg-info/requires.txt
raptus.securelogin.egg-info/top_level.txt
raptus.securelogin.egg-info/zip-safe
raptus/securelogin/__init__.py
raptus/securelogin/auth.py
raptus/securelogin/configure.zcml
raptus/securelogin/interfaces.py
raptus/securelogin/secure.py
raptus/securelogin/setuphandlers.py
raptus/securelogin/userdataschema.py
raptus/securelogin/utils.py
raptus/securelogin/Extensions/Install.py
raptus/securelogin/Extensions/__init__.py
raptus/securelogin/browser/__init__.py
raptus/securelogin/browser/configlet.py
raptus/securelogin/browser/configure.zcml
raptus/securelogin/locales/raptus.securelogin.pot
raptus/securelogin/locales/de/LC_MESSAGES/raptus.securelogin.mo
raptus/securelogin/locales/de/LC_MESSAGES/raptus.securelogin.po
raptus/securelogin/profiles/default/componentregistry.xml
raptus/securelogin/profiles/default/controlpanel.xml
raptus/securelogin/profiles/default/memberdata_properties.xml
raptus/securelogin/profiles/default/metadata.xml
raptus/securelogin/profiles/default/propertiestool.xml
raptus/securelogin/profiles/default/raptus.securelogin_various.txt
raptus/securelogin/profiles/default/skins.xml
raptus/securelogin/profiles/uninstall/componentregistry.xml
raptus/securelogin/profiles/uninstall/metadata.xml
raptus/securelogin/profiles/uninstall/raptus.securelogin_uninstall.txt
raptus/securelogin/skins/raptus_securelogin/login_form.cpt
raptus/securelogin/skins/raptus_securelogin/login_form.cpt.metadata
raptus/securelogin/skins/raptus_securelogin/login_form_validate.vpy
raptus/securelogin/skins/raptus_securelogin/login_form_validate.vpy.metadata
raptus/securelogin/zmi/SecureLoginCookieAuthHelperForm.zpt