Metadata-Version: 1.0
Name: raptus.securelogin
Version: 1.0a2
Summary: Provides a more secure login procedure for Plone for a defined set of groups.
Home-page: https://svn.plone.org/svn/collective/raptus.securelogin
Author: Raptus AG
Author-email: dev@raptus.com
License: GPL
Platform: UNKNOWN
Classifier: Programming Language :: Python
Classifier: Topic :: Software Development :: Libraries :: Python Modules
